[
    {
        "title": "A Horizon-Adaptive Benchmarking Framework for Long-Term Reservoir Storage Forecasting Using Physics-Informed Transformers and Machine Learning",
        "author": "Erişkin, E.",
        "year": "2026",
        "index": "other",
        "doi": "10.1007/s11269-025-04399-w",
        "scopus_link": "https://www.scopus.com/record/display.uri?eid=2-s2.0-105026208678"
    },
    {
        "title": "Using Ensemble Machine Learning to Estimate International Roughness Index of Asphalt Pavements",
        "author": "Erişkin, E.",
        "year": "2024",
        "index": "other",
        "doi": "10.1007/s40996-023-01320-6",
        "scopus_link": "https://www.scopus.com/record/display.uri?eid=2-s2.0-85180654047"
    },
    {
        "title": "Predicting Hydrological Droughts of Long-Narrow Type Drainage Basin Using Monte Carlo Technique",
        "author": "Erişkin, E.",
        "year": "2024",
        "index": "other",
        "doi": "10.1061/JHYEFF.HEENG-6144",
        "scopus_link": "https://www.scopus.com/record/display.uri?eid=2-s2.0-85190527987"
    },
    {
        "title": "Collaborative Game-Theoretic Optimization of Public Transport Fare Policies: A Global Framework for Sustainable Urban Mobility",
        "author": "Erişkin, E.",
        "year": "2024",
        "index": "sci",
        "doi": "10.3390/SU162411199",
        "wos_link": "https://www.webofscience.com/wos/woscc/full-record/WOS:001386540200001",
        "scopus_link": "https://www.scopus.com/record/display.uri?eid=2-s2.0-85213213330"
    },
    {
        "title": "Replacement of signalized traffic network design with Hamiltonian roads: delay? Nevermind",
        "author": "Erişkin, E.",
        "year": "2023",
        "index": "other",
        "doi": "10.1007/s00500-022-07735-z",
        "scopus_link": "https://www.scopus.com/record/display.uri?eid=2-s2.0-85144199026"
    },
    {
        "title": "Importance of A-pillars of vehicles during intersection approach",
        "author": "Erişkin, E.",
        "year": "2023",
        "index": "other",
        "doi": "10.51513/jitsa.1104161",
        "trdizin_link": "https://search.trdizin.gov.tr/tr/yayin/detay/1162079"
    },
    {
        "title": "Accident Severity Prediction in Big Data Using Auto-Machine Learning",
        "author": "Erişkin, E.",
        "year": "2023",
        "index": "other",
        "doi": "10.24200/sci.2023.60144.6626"
    },
    {
        "title": "Investigation of waste quartz sand as filler in hot-mix asphalt",
        "author": "Erişkin, E.",
        "year": "2022",
        "index": "other",
        "doi": "10.1016/j.conbuildmat.2022.128004",
        "scopus_link": "https://www.scopus.com/record/display.uri?eid=2-s2.0-85131455218"
    },
    {
        "title": "Prediction of Road Visibility Based on Meteorological Parameters by Machine Learning Methods",
        "author": "Erişkin, E.",
        "year": "2022",
        "index": "other",
        "doi": "10.31590/ejosat.1082868"
    },
    {
        "title": "Development of dynamic traffic signal control based on Monte Carlo simulation approach",
        "author": "Erişkin, E.",
        "year": "2022",
        "index": "sci",
        "doi": "10.1016/J.MEASUREMENT.2021.110591",
        "wos_link": "https://www.webofscience.com/wos/woscc/full-record/WOS:000742841900008",
        "scopus_link": "https://www.scopus.com/record/display.uri?eid=2-s2.0-85121217597"
    },
    {
        "title": "Bitumen expanding using bio-oil product of rose pulp’s pyrolysis process",
        "author": "Erişkin, E.",
        "year": "2020",
        "index": "other",
        "doi": "10.1016/j.conbuildmat.2020.118721",
        "scopus_link": "https://www.scopus.com/record/display.uri?eid=2-s2.0-85082136200"
    },
    {
        "title": "Evaluating mechanical properties of bitumen and hot mix asphalt modified with nano ferric oxide",
        "author": "Erişkin, E.",
        "year": "2020",
        "index": "other",
        "doi": "10.1016/j.conbuildmat.2019.117381",
        "scopus_link": "https://www.scopus.com/record/display.uri?eid=2-s2.0-85074557301"
    },
    {
        "title": "Increasing the visibility of roads using phosphorous paint",
        "author": "Erişkin, E.",
        "year": "2019",
        "index": "other",
        "doi": "10.1080/14680629.2017.1374999",
        "scopus_link": "https://www.scopus.com/record/display.uri?eid=2-s2.0-85029426588"
    },
    {
        "title": "Examination of the Effect of Superhydrophobic Coated Pavement under Wet Conditions",
        "author": "Erişkin, E.",
        "year": "2017",
        "index": "other",
        "doi": "10.1016/j.proeng.2017.04.411",
        "scopus_link": "https://www.scopus.com/record/display.uri?eid=2-s2.0-85020835208"
    },
    {
        "title": "Optimization of Traffic Signal Timing at Oversaturated Intersections Using Elimination Pairing System",
        "author": "Erişkin, E.",
        "year": "2017",
        "index": "other",
        "doi": "10.1016/j.proeng.2017.04.378",
        "scopus_link": "https://www.scopus.com/record/display.uri?eid=2-s2.0-85020493749"
    },
    {
        "title": "Waste frying oil modified bitumen usage for sustainable hot mix asphalt pavement",
        "author": "Erişkin, E.",
        "year": "2017",
        "index": "other",
        "doi": "10.1016/j.acme.2017.03.006",
        "scopus_link": "https://www.scopus.com/record/display.uri?eid=2-s2.0-85018634577"
    },
    {
        "title": "Utility of polyparaphenylene terephtalamide fiber in hot mix asphalt as a fiber",
        "author": "Erişkin, E.",
        "year": "2016",
        "index": "other",
        "doi": "10.1016/j.conbuildmat.2015.12.193"
    },
    {
        "title": "Utilization of Arundo donax in Hot Mix Asphalt as a fiber",
        "author": "Erişkin, E.",
        "year": "2016",
        "index": "sci",
        "doi": "10.1016/J.CONBUILDMAT.2016.08.147",
        "wos_link": "https://www.webofscience.com/wos/woscc/full-record/WOS:000385600100098",
        "scopus_link": "https://www.scopus.com/record/display.uri?eid=2-s2.0-84984973170"
    },
    {
        "title": "Estimating Pavement Temperature Using Machine Learning Models Based on Climatic Data",
        "author": "Terzi ",
        "year": "2025",
        "index": "scopus",
        "doi": "10.1061/9780784486214.036",
        "scopus_link": "https://www.scopus.com/record/display.uri?eid=2-s2.0-105010402575"
    },
    {
        "title": "An alternative approach for increasing the visibility of roads",
        "author": "Terzi S.",
        "year": "2024",
        "index": "scopus",
        "doi": "10.7764/RDLC.23.2.203",
        "scopus_link": "https://www.scopus.com/record/display.uri?eid=2-s2.0-85203088073"
    },
    {
        "title": "Investigation the Usability of Garnet as Filler Material in Hot Mix Asphalt",
        "author": "Karahancer S.",
        "year": "2020",
        "index": "scopus",
        "doi": "10.1007/978-981-15-2349-6_60",
        "scopus_link": "https://www.scopus.com/record/display.uri?eid=2-s2.0-85085204877"
    },
    {
        "title": "Expanded Glass Usability in Hot-Mix Asphalt as Fine Aggregate",
        "author": "Karahancer S.",
        "year": "2020",
        "index": "scopus",
        "doi": "10.1007/978-981-15-2349-6_54",
        "scopus_link": "https://www.scopus.com/record/display.uri?eid=2-s2.0-85085193242"
    },
    {
        "title": "Utility of Aramid, Polyolefin and Polypropylene Combination in Hot Mix Asphalt as a Fiber Material",
        "author": "Karahancer B.",
        "year": "2020",
        "index": "scopus",
        "doi": "10.1007/978-981-15-2349-6_61",
        "scopus_link": "https://www.scopus.com/record/display.uri?eid=2-s2.0-85085218062"
    },
    {
        "title": "Moisture Susceptibility of Nano-Al2O3 and SiO2 Modified Asphalt Mixtures",
        "author": "Karahancer S.",
        "year": "2019",
        "index": "scopus",
        "doi": "10.1061/9780784482469.013",
        "scopus_link": "https://www.scopus.com/record/display.uri?eid=2-s2.0-85073903849"
    },
    {
        "title": "Sulphur factory waste usability in hot mix asphalt as filler material",
        "author": "Karahancer S.",
        "year": "2018",
        "index": "scopus",
        "doi": "",
        "scopus_link": "https://www.scopus.com/record/display.uri?eid=2-s2.0-85061295763"
    },
    {
        "title": "Modelling Marshall Stability of fiber reinforced asphalt mixtures with ANFIS",
        "author": "Morova N.",
        "year": "2017",
        "index": "scopus",
        "doi": "10.1109/INISTA.2017.8001152",
        "scopus_link": "https://www.scopus.com/record/display.uri?eid=2-s2.0-85030233095"
    },
    {
        "title": "Estimation of specific gravity with penetration and penetration index parameters by artificial neural network",
        "author": "Serin S.",
        "year": "2017",
        "index": "scopus",
        "doi": "10.21533/pen.v5i2.106",
        "scopus_link": "https://www.scopus.com/record/display.uri?eid=2-s2.0-85035317532"
    },
    {
        "title": "Comparing cbr values obtained from field with laboratory test results",
        "author": "Karahancer S.",
        "year": "2017",
        "index": "scopus",
        "doi": "",
        "scopus_link": "https://www.scopus.com/record/display.uri?eid=2-s2.0-85058517582"
    },
    {
        "title": "Marshall stability estimating using artificial neural network with polyparaphenylene terephtalamide fibre rate",
        "author": "Karahancer S.",
        "year": "2016",
        "index": "scopus",
        "doi": "10.1109/INISTA.2016.7571848",
        "scopus_link": "https://www.scopus.com/record/display.uri?eid=2-s2.0-84992046827"
    },
    {
        "title": "Başlıksız Yayın",
        "author": "Erişkin, E., Erişkin, E., Erişkin, E.",
        "year": "2025",
        "index": "trdizin",
        "doi": "10.54875/jarss.2025.76093",
        "trdizin_link": "https://search.trdizin.gov.tr/tr/yayin/detay/1334749"
    },
    {
        "title": "Başlıksız Yayın",
        "author": "Erişkin, E.",
        "year": "2025",
        "index": "trdizin",
        "doi": "10.32925/tday.2025.128",
        "trdizin_link": "https://search.trdizin.gov.tr/tr/yayin/detay/1319946"
    },
    {
        "title": "Başlıksız Yayın",
        "author": "Erişkin, E.",
        "year": "2025",
        "index": "trdizin",
        "doi": "10.62425/turcology.1490243",
        "trdizin_link": "https://search.trdizin.gov.tr/tr/yayin/detay/1313433"
    },
    {
        "title": "Başlıksız Yayın",
        "author": "Erişkin, E., Erişkin, E.",
        "year": "2025",
        "index": "trdizin",
        "doi": "10.17753/sosekev.1512500",
        "trdizin_link": "https://search.trdizin.gov.tr/tr/yayin/detay/1307224"
    },
    {
        "title": "Başlıksız Yayın",
        "author": "Erişkin, E.",
        "year": "2024",
        "index": "trdizin",
        "doi": "",
        "trdizin_link": "https://search.trdizin.gov.tr/tr/yayin/detay/36807"
    },
    {
        "title": "Başlıksız Yayın",
        "author": "Erişkin, E.",
        "year": "2024",
        "index": "trdizin",
        "doi": "10.53635/jit.1563541",
        "trdizin_link": "https://search.trdizin.gov.tr/tr/yayin/detay/1288605"
    },
    {
        "title": "Başlıksız Yayın",
        "author": "Erişkin, E.",
        "year": "2024",
        "index": "trdizin",
        "doi": "10.30561/sinopusd.1542329",
        "trdizin_link": "https://search.trdizin.gov.tr/tr/yayin/detay/1283694"
    },
    {
        "title": "Başlıksız Yayın",
        "author": "Erişkin, E., Erişkin, E.",
        "year": "2024",
        "index": "trdizin",
        "doi": "10.34248/bsengineering.1532507",
        "trdizin_link": "https://search.trdizin.gov.tr/tr/yayin/detay/1280888"
    },
    {
        "title": "Başlıksız Yayın",
        "author": "Erişkin, E., Erişkin, E.",
        "year": "2024",
        "index": "trdizin",
        "doi": "10.54996/anatolianjem.1404434",
        "trdizin_link": "https://search.trdizin.gov.tr/tr/yayin/detay/1267866"
    },
    {
        "title": "Başlıksız Yayın",
        "author": "Erişkin, E., Erişkin, E., Erişkin, E., Erişkin, E., Erişkin, E., Erişkin, E., Erişkin, E., Erişkin, E., Erişkin, E., Erişkin, E., Erişkin, E., Erişkin, E., Erişkin, E.",
        "year": "2024",
        "index": "trdizin",
        "doi": "10.5578/ced.20240303",
        "trdizin_link": "https://search.trdizin.gov.tr/tr/yayin/detay/1263260"
    },
    {
        "title": "Başlıksız Yayın",
        "author": "Erişkin, E., Erişkin, E.",
        "year": "2024",
        "index": "trdizin",
        "doi": "10.5505/TurkHijyen.2024.04874",
        "trdizin_link": "https://search.trdizin.gov.tr/tr/yayin/detay/1242672"
    },
    {
        "title": "Başlıksız Yayın",
        "author": "Erişkin, E., Erişkin, E., Erişkin, E., Erişkin, E., Erişkin, E., Erişkin, E., Erişkin, E., Erişkin, E., Erişkin, E.",
        "year": "2024",
        "index": "trdizin",
        "doi": "122R016",
        "trdizin_link": "https://search.trdizin.gov.tr/tr/yayin/detay/1237804"
    },
    {
        "title": "Başlıksız Yayın",
        "author": "Erişkin, E., Erişkin, E.",
        "year": "2023",
        "index": "trdizin",
        "doi": "10.29228/Joh.70900",
        "trdizin_link": "https://search.trdizin.gov.tr/tr/yayin/detay/1340624"
    },
    {
        "title": "Başlıksız Yayın",
        "author": "Erişkin, E., Erişkin, E., Erişkin, E., Erişkin, E., Erişkin, E., Erişkin, E., Erişkin, E., Erişkin, E., Erişkin, E., Erişkin, E.",
        "year": "2023",
        "index": "trdizin",
        "doi": "121N060",
        "trdizin_link": "https://search.trdizin.gov.tr/tr/yayin/detay/1241364"
    },
    {
        "title": "Başlıksız Yayın",
        "author": "Erişkin, E.",
        "year": "2023",
        "index": "trdizin",
        "doi": "10.29000/rumelide.1379380",
        "trdizin_link": "https://search.trdizin.gov.tr/tr/yayin/detay/1209533"
    },
    {
        "title": "Başlıksız Yayın",
        "author": "Erişkin, E., Erişkin, E., Erişkin, E., Erişkin, E., Erişkin, E., Erişkin, E., Erişkin, E., Erişkin, E., Erişkin, E., Erişkin, E., Erişkin, E., Erişkin, E.",
        "year": "2023",
        "index": "trdizin",
        "doi": "10.5578/flora.20239708",
        "trdizin_link": "https://search.trdizin.gov.tr/tr/yayin/detay/1203865"
    },
    {
        "title": "Başlıksız Yayın",
        "author": "Erişkin, E.",
        "year": "2023",
        "index": "trdizin",
        "doi": "10.35408/comuybd.1231675",
        "trdizin_link": "https://search.trdizin.gov.tr/tr/yayin/detay/1202381"
    },
    {
        "title": "Başlıksız Yayın",
        "author": "Erişkin, E.",
        "year": "2023",
        "index": "trdizin",
        "doi": "10.14744/scie.2022.46504",
        "trdizin_link": "https://search.trdizin.gov.tr/tr/yayin/detay/1175059"
    },
    {
        "title": "Başlıksız Yayın",
        "author": "Erişkin, E.",
        "year": "2022",
        "index": "trdizin",
        "doi": "10.5336/mdethic.2021-86061",
        "trdizin_link": "https://search.trdizin.gov.tr/tr/yayin/detay/524561"
    },
    {
        "title": "Başlıksız Yayın",
        "author": "Erişkin, E., Erişkin, E., Erişkin, E.",
        "year": "2022",
        "index": "trdizin",
        "doi": "10.14744/GKDAD.2021.27676",
        "trdizin_link": "https://search.trdizin.gov.tr/tr/yayin/detay/516694"
    },
    {
        "title": "Başlıksız Yayın",
        "author": "Erişkin, E., Erişkin, E., Erişkin, E.",
        "year": "2022",
        "index": "trdizin",
        "doi": "10.18521/ktd.1039175",
        "trdizin_link": "https://search.trdizin.gov.tr/tr/yayin/detay/1207860"
    },
    {
        "title": "Başlıksız Yayın",
        "author": "Erişkin, E., Erişkin, E.",
        "year": "2022",
        "index": "trdizin",
        "doi": "10.31196/huvfd.1147383",
        "trdizin_link": "https://search.trdizin.gov.tr/tr/yayin/detay/1145220"
    },
    {
        "title": "Başlıksız Yayın",
        "author": "Erişkin, E.",
        "year": "2021",
        "index": "trdizin",
        "doi": "10.35341/afet.982097",
        "trdizin_link": "https://search.trdizin.gov.tr/tr/yayin/detay/489207"
    },
    {
        "title": "Başlıksız Yayın",
        "author": "Erişkin, E., Erişkin, E.",
        "year": "2021",
        "index": "trdizin",
        "doi": "10.18521/ktd.912698",
        "trdizin_link": "https://search.trdizin.gov.tr/tr/yayin/detay/467290"
    },
    {
        "title": "Başlıksız Yayın",
        "author": "Erişkin, E.",
        "year": "2021",
        "index": "trdizin",
        "doi": "10.35193/bseufbd.885635",
        "trdizin_link": "https://search.trdizin.gov.tr/tr/yayin/detay/465069"
    },
    {
        "title": "Başlıksız Yayın",
        "author": "Erişkin, E., Erişkin, E., Erişkin, E., Erişkin, E., Erişkin, E.",
        "year": "2021",
        "index": "trdizin",
        "doi": "10.14235/bas.galenos.2020.4838",
        "trdizin_link": "https://search.trdizin.gov.tr/tr/yayin/detay/425703"
    },
    {
        "title": "Başlıksız Yayın",
        "author": "Erişkin, E., Erişkin, E., Erişkin, E., Erişkin, E., Erişkin, E., Erişkin, E., Erişkin, E., Erişkin, E.",
        "year": "2021",
        "index": "trdizin",
        "doi": "119S348",
        "trdizin_link": "https://search.trdizin.gov.tr/tr/yayin/detay/1235501"
    },
    {
        "title": "Başlıksız Yayın",
        "author": "Erişkin, E.",
        "year": "2020",
        "index": "trdizin",
        "doi": "10.5222/jarss.2020.65477",
        "trdizin_link": "https://search.trdizin.gov.tr/tr/yayin/detay/424892"
    },
    {
        "title": "Başlıksız Yayın",
        "author": "Erişkin, E., Erişkin, E.",
        "year": "2020",
        "index": "trdizin",
        "doi": "10.26677/TR1010.2020.480ISSN: 2587–0890 Dergi web sayfası: https://www.tu",
        "trdizin_link": "https://search.trdizin.gov.tr/tr/yayin/detay/422693"
    },
    {
        "title": "Başlıksız Yayın",
        "author": "Erişkin, E., Erişkin, E., Erişkin, E., Erişkin, E.",
        "year": "2020",
        "index": "trdizin",
        "doi": "10.25282/ted.689108",
        "trdizin_link": "https://search.trdizin.gov.tr/tr/yayin/detay/413247"
    },
    {
        "title": "Başlıksız Yayın",
        "author": "Erişkin, E., Erişkin, E., Erişkin, E., Erişkin, E.",
        "year": "2020",
        "index": "trdizin",
        "doi": "10.29130/dubited.686047",
        "trdizin_link": "https://search.trdizin.gov.tr/tr/yayin/detay/390821"
    },
    {
        "title": "Başlıksız Yayın",
        "author": "Erişkin, E., Erişkin, E., Erişkin, E.",
        "year": "2020",
        "index": "trdizin",
        "doi": "10.31125/hunhemsire.776491",
        "trdizin_link": "https://search.trdizin.gov.tr/tr/yayin/detay/388217"
    },
    {
        "title": "Başlıksız Yayın",
        "author": "Erişkin, E., Erişkin, E., Erişkin, E., Erişkin, E., Erişkin, E., Erişkin, E.",
        "year": "2019",
        "index": "trdizin",
        "doi": "10.21923/jesd.553502",
        "trdizin_link": "https://search.trdizin.gov.tr/tr/yayin/detay/398662"
    },
    {
        "title": "Başlıksız Yayın",
        "author": "Erişkin, E.",
        "year": "2018",
        "index": "trdizin",
        "doi": "10.5505/jems.2018.53325",
        "trdizin_link": "https://search.trdizin.gov.tr/tr/yayin/detay/384867"
    },
    {
        "title": "Başlıksız Yayın",
        "author": "Erişkin, E.",
        "year": "2018",
        "index": "trdizin",
        "doi": "10.21550/sosbilder.387657",
        "trdizin_link": "https://search.trdizin.gov.tr/tr/yayin/detay/352065"
    },
    {
        "title": "Başlıksız Yayın",
        "author": "Erişkin, E., Erişkin, E., Erişkin, E., Erişkin, E., Erişkin, E.",
        "year": "2018",
        "index": "trdizin",
        "doi": "10.21923/jesd.306098",
        "trdizin_link": "https://search.trdizin.gov.tr/tr/yayin/detay/326723"
    },
    {
        "title": "Başlıksız Yayın",
        "author": "Erişkin, E., Erişkin, E., Erişkin, E.",
        "year": "2018",
        "index": "trdizin",
        "doi": "10.21325/jotags.2018.231",
        "trdizin_link": "https://search.trdizin.gov.tr/tr/yayin/detay/311869"
    },
    {
        "title": "Başlıksız Yayın",
        "author": "Erişkin, E., Erişkin, E., Erişkin, E., Erişkin, E., Erişkin, E., Erişkin, E.",
        "year": "2018",
        "index": "trdizin",
        "doi": "10.17941/agd.498555",
        "trdizin_link": "https://search.trdizin.gov.tr/tr/yayin/detay/298752"
    },
    {
        "title": "Başlıksız Yayın",
        "author": "Erişkin, E., Erişkin, E.",
        "year": "2018",
        "index": "trdizin",
        "doi": "10.24011/barofd.425466",
        "trdizin_link": "https://search.trdizin.gov.tr/tr/yayin/detay/286414"
    }
]