[
    {
        "title": "A Horizon-Adaptive Benchmarking Framework for Long-Term Reservoir Storage Forecasting Using Physics-Informed Transformers and Machine Learning",
        "author": "Erişkin, E.",
        "year": "2026",
        "index": "other",
        "doi": "10.1007/s11269-025-04399-w"
    },
    {
        "title": "Using Ensemble Machine Learning to Estimate International Roughness Index of Asphalt Pavements",
        "author": "Erişkin, E.",
        "year": "2024",
        "index": "other",
        "doi": "10.1007/s40996-023-01320-6"
    },
    {
        "title": "Predicting Hydrological Droughts of Long-Narrow Type Drainage Basin Using Monte Carlo Technique",
        "author": "Erişkin, E.",
        "year": "2024",
        "index": "other",
        "doi": "10.1061/JHYEFF.HEENG-6144"
    },
    {
        "title": "Collaborative Game-Theoretic Optimization of Public Transport Fare Policies: A Global Framework for Sustainable Urban Mobility",
        "author": "Erişkin, E.",
        "year": "2024",
        "index": "sci",
        "doi": "10.3390/SU162411199",
        "wos_link": "https://www.webofscience.com/wos/woscc/full-record/WOS:001386540200001"
    },
    {
        "title": "Replacement of signalized traffic network design with Hamiltonian roads: delay? Nevermind",
        "author": "Erişkin, E.",
        "year": "2023",
        "index": "other",
        "doi": "10.1007/s00500-022-07735-z"
    },
    {
        "title": "Importance of A-pillars of vehicles during intersection approach",
        "author": "Erişkin, E.",
        "year": "2023",
        "index": "other",
        "doi": "10.51513/jitsa.1104161"
    },
    {
        "title": "Accident Severity Prediction in Big Data Using Auto-Machine Learning",
        "author": "Erişkin, E.",
        "year": "2023",
        "index": "other",
        "doi": "10.24200/sci.2023.60144.6626"
    },
    {
        "title": "Investigation of waste quartz sand as filler in hot-mix asphalt",
        "author": "Erişkin, E.",
        "year": "2022",
        "index": "other",
        "doi": "10.1016/j.conbuildmat.2022.128004"
    },
    {
        "title": "Prediction of Road Visibility Based on Meteorological Parameters by Machine Learning Methods",
        "author": "Erişkin, E.",
        "year": "2022",
        "index": "other",
        "doi": "10.31590/ejosat.1082868"
    },
    {
        "title": "Development of dynamic traffic signal control based on Monte Carlo simulation approach",
        "author": "Erişkin, E.",
        "year": "2022",
        "index": "sci",
        "doi": "10.1016/J.MEASUREMENT.2021.110591",
        "wos_link": "https://www.webofscience.com/wos/woscc/full-record/WOS:000742841900008"
    },
    {
        "title": "Bitumen expanding using bio-oil product of rose pulp’s pyrolysis process",
        "author": "Erişkin, E.",
        "year": "2020",
        "index": "other",
        "doi": "10.1016/j.conbuildmat.2020.118721"
    },
    {
        "title": "Evaluating mechanical properties of bitumen and hot mix asphalt modified with nano ferric oxide",
        "author": "Erişkin, E.",
        "year": "2020",
        "index": "other",
        "doi": "10.1016/j.conbuildmat.2019.117381"
    },
    {
        "title": "Increasing the visibility of roads using phosphorous paint",
        "author": "Erişkin, E.",
        "year": "2019",
        "index": "other",
        "doi": "10.1080/14680629.2017.1374999"
    },
    {
        "title": "Examination of the Effect of Superhydrophobic Coated Pavement under Wet Conditions",
        "author": "Erişkin, E.",
        "year": "2017",
        "index": "other",
        "doi": "10.1016/j.proeng.2017.04.411"
    },
    {
        "title": "Optimization of Traffic Signal Timing at Oversaturated Intersections Using Elimination Pairing System",
        "author": "Erişkin, E.",
        "year": "2017",
        "index": "other",
        "doi": "10.1016/j.proeng.2017.04.378"
    },
    {
        "title": "Waste frying oil modified bitumen usage for sustainable hot mix asphalt pavement",
        "author": "Erişkin, E.",
        "year": "2017",
        "index": "other",
        "doi": "10.1016/j.acme.2017.03.006"
    },
    {
        "title": "Utility of polyparaphenylene terephtalamide fiber in hot mix asphalt as a fiber",
        "author": "Erişkin, E.",
        "year": "2016",
        "index": "other",
        "doi": "10.1016/j.conbuildmat.2015.12.193"
    },
    {
        "title": "Utilization of Arundo donax in Hot Mix Asphalt as a fiber",
        "author": "Erişkin, E.",
        "year": "2016",
        "index": "sci",
        "doi": "10.1016/J.CONBUILDMAT.2016.08.147",
        "wos_link": "https://www.webofscience.com/wos/woscc/full-record/WOS:000385600100098"
    }
]